eoq2/__init__.py
eoq2/action/__init__.py
eoq2/action/action.py
eoq2/action/call.py
eoq2/action/callhandler.py
eoq2/action/callmanager.py
eoq2/action/cmdrunnerbasedcallmanager.py
eoq2/action/util.py
eoq2/action/externalpy/__init__.py
eoq2/action/externalpy/externalpyscripthandler.py
eoq2/command/__init__.py
eoq2/command/command.py
eoq2/command/commandrunner.py
eoq2/command/diff.py
eoq2/command/result.py
eoq2/domain/__init__.py
eoq2/domain/cmdrunnerbaseddomain.py
eoq2/domain/domain.py
eoq2/domain/local/__init__.py
eoq2/domain/local/localmdbdomain.py
eoq2/domain/multiprocessing/__init__.py
eoq2/domain/multiprocessing/multiprocessingcallmanager.py
eoq2/domain/multiprocessing/multiprocessingdomainclient.py
eoq2/domain/multiprocessing/multiprocessingdomainhost.py
eoq2/domain/remote/__init__.py
eoq2/domain/remote/websocketdomain.py
eoq2/event/__init__.py
eoq2/event/event.py
eoq2/frame/__init__.py
eoq2/frame/domainframehandler.py
eoq2/frame/frame.py
eoq2/frame/framehandler.py
eoq2/frame/multiversionframehandler.py
eoq2/legacy/__init__.py
eoq2/legacy/legacy.py
eoq2/mdb/__init__.py
eoq2/mdb/mdb.py
eoq2/mdb/mdbaccessor.py
eoq2/mdb/nocodec.py
eoq2/mdb/valuecodec.py
eoq2/mdb/pyecore/__init__.py
eoq2/mdb/pyecore/pyecoreidcodec.py
eoq2/mdb/pyecore/pyecoremdb.py
eoq2/mdb/pyecore/pyecoremdbaccessor.py
eoq2/mdb/pyecore/pyecoresimpleobjectcodec.py
eoq2/mdb/pyecore/pyecoresinglefilemdb.py
eoq2/mdb/pyecore/pyecoresinglefilemdbprovider.py
eoq2/mdb/pyecore/pyecoreworkspacemdbprovider.py
eoq2/mdb/pyecore/constraintmodel/__init__.py
eoq2/mdb/pyecore/constraintmodel/constraintmodel.py
eoq2/mdb/pyecore/workspacemdbmodel/__init__.py
eoq2/mdb/pyecore/workspacemdbmodel/workspacemdbmodel.py
eoq2/mdb/pyecore/xmlresourcemodel/__init__.py
eoq2/mdb/pyecore/xmlresourcemodel/xmlresourcemodel.py
eoq2/query/__init__.py
eoq2/query/query.py
eoq2/query/queryrunner.py
eoq2/serialization/__init__.py
eoq2/serialization/jsonserializer.py
eoq2/serialization/jsserializer.py
eoq2/serialization/pyserializer.py
eoq2-2.2.17.2.dist-info/LICENSE
eoq2-2.2.17.2.dist-info/METADATA
eoq2-2.2.17.2.dist-info/WHEEL
eoq2-2.2.17.2.dist-info/top_level.txt
eoq2-2.2.17.2.dist-info/RECORD
