Metadata-Version: 2.1
Name: eoq2
Version: 2.2.17.2
Summary: Essential Object Query - a framework to access ecore models
Author-email: Bjoern Annighoefer <bjoern.annighoefer@ils.uni-stuttgart.de>
Project-URL: Homepage, https://gitlab.com/eoq/py/eoq2
Project-URL: Issues, https://gitlab.com/eoq/py/eoq2/-/issues
Classifier: Programming Language :: Python :: 3
Classifier: License :: OSI Approved :: MIT License
Classifier: Operating System :: OS Independent
Requires-Python: >=3.6
License-File: LICENSE
Requires-Dist: eoq1
Requires-Dist: pyecore
Requires-Dist: watchdog
